lungmask/__init__.py
lungmask/__main__.py
lungmask/logger.py
lungmask/mask.py
lungmask/resunet.py
lungmask/utils.py
lungmask-0.2.20.dist-info/LICENSE
lungmask-0.2.20.dist-info/METADATA
lungmask-0.2.20.dist-info/WHEEL
lungmask-0.2.20.dist-info/entry_points.txt
lungmask-0.2.20.dist-info/top_level.txt
lungmask-0.2.20.dist-info/RECORD
