Metadata-Version: 2.1
Name: lungmask
Version: 0.2.20
Summary: Package for automated lung segmentation in CT
Home-page: https://github.com/JoHof/lungmask
Author: Johannes Hofmanninger
Author-email: j.hofmanninger@gmail.com
Classifier: Programming Language :: Python :: 3
Classifier: Operating System :: OS Independent
Requires-Python: >=3.6
License-File: LICENSE
Requires-Dist: pydicom
Requires-Dist: numpy
Requires-Dist: torch
Requires-Dist: scipy
Requires-Dist: SimpleITK
Requires-Dist: tqdm
Requires-Dist: scikit-image
Requires-Dist: fill-voids
Requires-Dist: more-itertools
